intake_duckdb/__init__.py
intake_duckdb/base.py
intake_duckdb/catalog.py
intake_duckdb/transform.py
intake_duckdb-0.1.2.dist-info/LICENSE
intake_duckdb-0.1.2.dist-info/METADATA
intake_duckdb-0.1.2.dist-info/WHEEL
intake_duckdb-0.1.2.dist-info/entry_points.txt
intake_duckdb-0.1.2.dist-info/top_level.txt
intake_duckdb-0.1.2.dist-info/RECORD
