Metadata-Version: 2.1
Name: intake-duckdb
Version: 0.1.2
Summary: DuckDB plugin for Intake
Author: Blake Rosenthal
Maintainer-email: Blake Rosenthal <brosenthal@anaconda.com>
License: Copyright (c) 2023, Anaconda, Inc.
Keywords: intake,duckdb,duck
Requires-Python: >=3.8
License-File: LICENSE
Requires-Dist: intake
Requires-Dist: pandas
Requires-Dist: duckdb
Provides-Extra: docs
Requires-Dist: sphinx ; extra == 'docs'
Requires-Dist: sphinx-rtd-theme ; extra == 'docs'
Requires-Dist: numpydoc ; extra == 'docs'
Requires-Dist: entrypoints ; extra == 'docs'
Requires-Dist: myst-parser ; extra == 'docs'
Provides-Extra: test
Requires-Dist: pytest ; extra == 'test'
Requires-Dist: intake[server] ; extra == 'test'
Requires-Dist: python-snappy ; extra == 'test'
